s1282003_learn/__init__.py
s1282003_learn/statistics/__init__.py
s1282003_learn/statistics/frequenciesOfItems.py
s1282003_learn/visualization/__init__.py
s1282003_learn/visualization/heatMapItemsFrequencies.py
s1282003_learn-2023.8.5.3.dist-info/LICENSE
s1282003_learn-2023.8.5.3.dist-info/METADATA
s1282003_learn-2023.8.5.3.dist-info/WHEEL
s1282003_learn-2023.8.5.3.dist-info/top_level.txt
s1282003_learn-2023.8.5.3.dist-info/RECORD
